unifiedai/__init__.py
unifiedai/_async_client.py
unifiedai/_bedrock_compat.py
unifiedai/_cerebras_compat.py
unifiedai/_client.py
unifiedai/_context.py
unifiedai/_exceptions.py
unifiedai/_health.py
unifiedai/_logging.py
unifiedai/_retry.py
unifiedai/adapters/base.py
unifiedai/adapters/bedrock.py
unifiedai/adapters/cerebras.py
unifiedai/adapters/mappers.py
unifiedai/adapters/registry.py
unifiedai/core/comparison.py
unifiedai/metrics/emitter.py
unifiedai/models/comparison.py
unifiedai/models/config.py
unifiedai/models/model.py
unifiedai/models/request.py
unifiedai/models/response.py
unifiedai/models/stream.py
unifiedai/resilience/__init__.py
unifiedai/resilience/circuit_breaker.py
unifiedai_sdk-1.1.1.dist-info/METADATA
unifiedai_sdk-1.1.1.dist-info/WHEEL
unifiedai_sdk-1.1.1.dist-info/licenses/LICENSE
unifiedai_sdk-1.1.1.dist-info/RECORD
