Metadata-Version: 2.4
Name: unifiedai-sdk
Version: 1.1.1
Summary: Unified SDK for multi-provider LLM comparison (Cerebras, AWS Bedrock) with OpenAI-compatible interface.
Author-email: Your Team <team@example.com>
License: MIT
License-File: LICENSE
Keywords: bedrock,cerebras,comparison,llm,openai-compatible,sdk
Classifier: Development Status :: 4 - Beta
Classifier: Intended Audience :: Developers
Classifier: License :: OSI Approved :: MIT License
Classifier: Programming Language :: Python :: 3.9
Classifier: Programming Language :: Python :: 3.10
Classifier: Programming Language :: Python :: 3.11
Classifier: Programming Language :: Python :: 3.12
Requires-Python: >=3.9
Requires-Dist: boto3
Requires-Dist: cerebras-cloud-sdk>=0.5.0
Requires-Dist: httpx>=0.27.0
Requires-Dist: httpx[http2]
Requires-Dist: opentelemetry-api>=1.20.0
Requires-Dist: prometheus-client>=0.20.0
Requires-Dist: pybreaker>=1.0.0
Requires-Dist: pydantic>=2.0.0
Requires-Dist: structlog>=24.0.0
Requires-Dist: tenacity>=8.0.0
Provides-Extra: bedrock
Requires-Dist: boto3>=1.28.0; extra == 'bedrock'
Provides-Extra: dev
Requires-Dist: black>=24.0.0; extra == 'dev'
Requires-Dist: coverage[toml]>=7.0.0; extra == 'dev'
Requires-Dist: mypy>=1.8.0; extra == 'dev'
Requires-Dist: pre-commit>=3.0.0; extra == 'dev'
Requires-Dist: pytest-asyncio>=0.23.0; extra == 'dev'
Requires-Dist: pytest-benchmark>=4.0.0; extra == 'dev'
Requires-Dist: pytest-cov>=4.0.0; extra == 'dev'
Requires-Dist: pytest-html>=4.1.0; extra == 'dev'
Requires-Dist: pytest-mock>=3.12.0; extra == 'dev'
Requires-Dist: pytest-vcr>=1.0.0; extra == 'dev'
Requires-Dist: pytest>=8.0.0; extra == 'dev'
Requires-Dist: ruff>=0.3.0; extra == 'dev'
